{
  "employee": [
    {
      "id": 1,
      "name": "swapnil",
      "email": "swapnil@gmail.com",
      "phone": "9371131415",
      "active": true
    },
    {
      "name": "Sanket",
      "email": "sanket@gmail.com",
      "phone": "9511621176",
      "active": true,
      "id": 2
    },
    {
      "name": "Swaraj",
      "email": "swaraj@gmail.com",
      "phone": "9213151617",
      "active": true,
      "id": 3
    },
    {
      "name": "Akshata",
      "email": "akshata@gmail.com",
      "phone": "7022451617",
      "active": true,
      "id": 4
    },
    {
      "name": "Samrudhi",
      "email": "samrudhi@gmail.com",
      "phone": "8045631217",
      "active": true,
      "id": 5
    }
  ],
  "user": [
    {
      "id": "1",
      "userName": "Manish",
      "emailId": "manish@gmail.com",
      "password": "manish@123",
      "mobile": "9512112233"
    },
    {
      "id": "9jNKp7A",
      "emailId": "varsha@gmail.com",
      "userName": "varsha",
      "mobile": "9211445566",
      "password": "varsha@123"
    },
    {
      "emailId": "manik@gmail.com",
      "userName": "Manik",
      "mobile": "9440121314",
      "password": "manik@123",
      "id": "giUUArX"
    },
    {
      "emailId": "surekha@gmail.com",
      "userName": "surekha",
      "mobile": "9423556071",
      "password": "surekha@123",
      "id": "xSHMVr7"
    },
    {
      "emailId": "swapnil@gmail.com",
      "userName": "swapnil",
      "mobile": "7041121314",
      "password": "swapnil@12",
      "id": "dd5VVKW"
    },
    {
      "emailId": "priya@gmail.com",
      "userName": "priya",
      "mobile": "7512131415",
      "password": "priya@123",
      "id": "7gNgerS"
    },
    {
      "emailId": "omkar@gmail.com",
      "userName": "omkar",
      "mobile": "9312151617",
      "password": "omkar@123",
      "id": "xWuspn-"
    },
    {
      "emailId": "rahul@gmail.com",
      "userName": "rahul",
      "mobile": "9612151618",
      "password": "rahul@123",
      "id": "sJuPXuT"
    },
    {
      "emailId": "aniket@gmail.com",
      "userName": "aniket",
      "mobile": "9822131415",
      "password": "aniket@123",
      "id": "PuWee4_"
    }
  ]
}